trr265/None.py
trr265/__init__.py
trr265/_nbdev.py
trr265/behavior_control_congruency.py
trr265/core.py
trr265/data_provider.py
trr265/gbe.py
trr265/plotting.py
trr265/stats.py
trr265/validation_task.py
trr265/gbe/__init__.py
trr265/gbe/baseline_drinking.py
trr265/gbe/data_provider.py
trr265/gbe/ema_drinking.py
trr265/gbe/intense_sampling.py
trr265/gbe/participants.py
trr265/gbe/reliability.py
trr265/gbe/baseline_drinking/__init__.py
trr265/gbe/baseline_drinking/separate.py
trr265/gbe/ist/__init__.py
trr265/gbe/ist/data_provider.py
trr265/gbe/ist/reliability.py
trr265/gbe/ist/scoring.py
trr265/gbe/rtt/__init__.py
trr265/gbe/rtt/data_provider.py
trr265/gbe/rtt/reliability.py
trr265/gbe/rtt/scoring.py
trr265/gbe/rtt/singular_fit_inspection.py
trr265/gbe/sst/__init__.py
trr265/gbe/sst/data_provider.py
trr265/gbe/sst/reliability.py
trr265/gbe/sst/scoring.py
trr265/gbe/wm/__init__.py
trr265/gbe/wm/data_provider.py
trr265/gbe/wm/reliability.py
trr265/gbe/wm/scoring.py
trr265-0.0.10.dist-info/LICENSE
trr265-0.0.10.dist-info/METADATA
trr265-0.0.10.dist-info/WHEEL
trr265-0.0.10.dist-info/entry_points.txt
trr265-0.0.10.dist-info/top_level.txt
trr265-0.0.10.dist-info/RECORD
