Metadata-Version: 2.1
Name: trr265
Version: 0.0.10
Summary: The TRR 265 analysis pipeline.
Home-page: https://github.com/hgzech/trr265/tree/master/
Author: Hilmar Zech
Author-email: hgzech@gmail.com
License: Apache Software License 2.0
Keywords: trr265 sfb265
Platform: UNKNOWN
Classifier: Development Status :: 3 - Alpha
Classifier: Intended Audience :: Developers
Classifier: Natural Language :: English
Classifier: Programming Language :: Python :: 3.6
Classifier: Programming Language :: Python :: 3.7
Classifier: Programming Language :: Python :: 3.8
Classifier: License :: OSI Approved :: Apache Software License
Requires-Python: >=3.6
License-File: LICENSE
Requires-Dist: pip
Requires-Dist: packaging
Requires-Dist: bs4
Requires-Dist: pandas
Requires-Dist: numpy
Requires-Dist: pyarrow
Requires-Dist: openpyxl
Requires-Dist: lxml
Requires-Dist: matplotlib
Requires-Dist: seaborn
Requires-Dist: fastcore
Provides-Extra: dev
